check_reqs/__init__.py
check_reqs/__main__.py
check_reqs/check_reqs.py
check_reqs-1.0.0.dist-info/entry_points.txt
check_reqs-1.0.0.dist-info/LICENSE
check_reqs-1.0.0.dist-info/WHEEL
check_reqs-1.0.0.dist-info/METADATA
check_reqs-1.0.0.dist-info/RECORD
