Metadata-Version: 2.1
Name: check-reqs
Version: 1.0.0
Summary: Checks if all requirements from a file are installed in the current Python env
Home-page: https://github.com/renefritze/check_reqs
License: MIT
Author: renefritze
Author-email: coding@fritze.me
Requires-Python: >=3.7,<4.0
Classifier: Development Status :: 3 - Alpha
Classifier: Intended Audience :: Developers
Classifier: License :: OSI Approved :: MIT License
Classifier: Operating System :: OS Independent
Classifier: Programming Language :: Python :: 3
Classifier: Programming Language :: Python :: 3.10
Classifier: Programming Language :: Python :: 3.7
Classifier: Programming Language :: Python :: 3.8
Classifier: Programming Language :: Python :: 3.9
Classifier: Topic :: Software Development :: Libraries :: Python Modules
Requires-Dist: importlib_metadata (>=4.5.0,<5.0.0); python_version < "3.8"
Requires-Dist: rich (>=10.14,<13.0)
Requires-Dist: typer[all] (>=0.4,<0.6)
Project-URL: Repository, https://github.com/renefritze/check_reqs
